attrsfile/__init__.py
attrsfile/attrsfile.py
attrsfile-0.1.2.dist-info/LICENSE
attrsfile-0.1.2.dist-info/WHEEL
attrsfile-0.1.2.dist-info/METADATA
attrsfile-0.1.2.dist-info/RECORD
