Metadata-Version: 2.1
Name: attrsfile
Version: 0.1.2
Summary: A file mapper for attrs classes.
License: MIT
Author: Deniz Bozyigit
Author-email: deniz195@gmail.com
Requires-Python: >=3.7,<4.0
Classifier: License :: OSI Approved :: MIT License
Classifier: Programming Language :: Python :: 3
Classifier: Programming Language :: Python :: 3.7
Classifier: Programming Language :: Python :: 3.8
Classifier: Programming Language :: Python :: 3.9
Requires-Dist: attrs (>=20.3.0,<21.0.0)
Requires-Dist: cattrs (>=1.1.2,<2.0.0)
Requires-Dist: pre-commit (>=2.10.0,<3.0.0)
Requires-Dist: ruamel.yaml (>=0.16.12,<0.17.0)
